<?xml version="1.0" encoding="utf-8"?>
<!DOCTYPE hibernate-mapping PUBLIC "-//Hibernate/Hibernate Mapping DTD 3.0//EN"
                                   "http://hibernate.sourceforge.net/hibernate-mapping-3.0.dtd">
<!-- 
    Mapping file autogenerated by MyEclipse Persistence Tools
-->
<hibernate-mapping>
 <class name="org.yeahwa.news.model.UserNew" table="user_new">
  <composite-id mapped="false" unsaved-value="undefined">
   <key-property name="userid" type="string">
   	<column name="userid" length="20"></column>
   </key-property>
   <key-property name="newid" type="java.lang.String">
   <column length="20" name="newid"/>
  </key-property>
  <key-property name="viewdate" type="date">
   <column length="20" name="viewdate" sql-type="DATE"/>
  </key-property>
  <key-property name="newtitle" type="java.lang.String">
   <column length="500" name="newtitle"/>
  </key-property>
  <key-property name="newcontent" type="string">
   <column name="newcontent" sql-type="BLOB"/>
  </key-property>
  </composite-id>
 </class>
</hibernate-mapping>
